[
  {
    "id": "1782863633139fgjtnm0p7wn",
    "agentId": "coord_qa",
    "agentName": "Diana Test",
    "agentAvatar": "🔍",
    "action": "closed",
    "ticketKey": "MOCK-QA-561",
    "ticketSummary": "[QA] Validação: precisamos criar um jogo da memoria, e cada uma das cartas sao jogos, exemplo cobrinha, dama, velha e outros classicos... se uma pessoa achar o par, o adversario e ele joga aquele jogo, se ele for de par, mas se for jogo indivisual, o adversario deve jogar....",
    "at": "2026-06-30T23:53:53.139Z"
  },
  {
    "id": "1782863631620a9etf2jzs2q",
    "agentId": "coord_qa",
    "agentName": "Diana Test",
    "agentAvatar": "🔍",
    "action": "opened",
    "ticketKey": "...",
    "ticketSummary": "[QA] Validação: precisamos criar um jogo da memoria, e cada uma das cartas sao jogos, exemplo cobrinha, dama, velha e outros classicos... se uma pessoa achar o par, o adversario e ele joga aquele jogo, se ele for de par, mas se for jogo indivisual, o adversario deve jogar....",
    "at": "2026-06-30T23:53:51.620Z"
  },
  {
    "id": "1782863631616siy2t1s2a5",
    "agentId": "sr_dev",
    "agentName": "David Dev",
    "agentAvatar": "⚡",
    "action": "closed",
    "ticketKey": "MOCK-DEV-719",
    "ticketSummary": "[DEV] Implementação: precisamos criar um jogo da memoria, e cada uma das cartas sao jogos, exemplo cobrinha, dama, velha e outros classicos... se uma pessoa achar o par, o adversario e ele joga aquele jogo, se ele for de par, mas se for jogo indivisual, o adversario deve jogar....",
    "at": "2026-06-30T23:53:51.616Z"
  },
  {
    "id": "17828636306391dwpy88hu9bh",
    "agentId": "sr_dev",
    "agentName": "David Dev",
    "agentAvatar": "⚡",
    "action": "opened",
    "ticketKey": "...",
    "ticketSummary": "[DEV] Implementação: precisamos criar um jogo da memoria, e cada uma das cartas sao jogos, exemplo cobrinha, dama, velha e outros classicos... se uma pessoa achar o par, o adversario e ele joga aquele jogo, se ele for de par, mas se for jogo indivisual, o adversario deve jogar....",
    "at": "2026-06-30T23:53:50.639Z"
  },
  {
    "id": "1782863630637j94heppg10n",
    "agentId": "sr_ux",
    "agentName": "Elsa Pixel",
    "agentAvatar": "✨",
    "action": "closed",
    "ticketKey": "MOCK-UX-542",
    "ticketSummary": "[UX] Design: precisamos criar um jogo da memoria, e cada uma das cartas sao jogos, exemplo cobrinha, dama, velha e outros classicos... se uma pessoa achar o par, o adversario e ele joga aquele jogo, se ele for de par, mas se for jogo indivisual, o adversario deve jogar....",
    "at": "2026-06-30T23:53:50.637Z"
  },
  {
    "id": "1782863629240smq1m6i5t8",
    "agentId": "sr_ux",
    "agentName": "Elsa Pixel",
    "agentAvatar": "✨",
    "action": "opened",
    "ticketKey": "...",
    "ticketSummary": "[UX] Design: precisamos criar um jogo da memoria, e cada uma das cartas sao jogos, exemplo cobrinha, dama, velha e outros classicos... se uma pessoa achar o par, o adversario e ele joga aquele jogo, se ele for de par, mas se for jogo indivisual, o adversario deve jogar....",
    "at": "2026-06-30T23:53:49.240Z"
  },
  {
    "id": "178286362923891typ83ppm",
    "agentId": "mgr_prod",
    "agentName": "Sarah Backlog",
    "agentAvatar": "📋",
    "action": "closed",
    "ticketKey": "MOCK-PM-492",
    "ticketSummary": "[PM] Planejamento: precisamos criar um jogo da memoria, e cada uma das cartas sao jogos, exemplo cobrinha, dama, velha e outros classicos... se uma pessoa achar o par, o adversario e ele joga aquele jogo, se ele for de par, mas se for jogo indivisual, o adversario deve jogar....",
    "at": "2026-06-30T23:53:49.238Z"
  },
  {
    "id": "178286362754377icuwwz1m8",
    "agentId": "mgr_prod",
    "agentName": "Sarah Backlog",
    "agentAvatar": "📋",
    "action": "opened",
    "ticketKey": "...",
    "ticketSummary": "[PM] Planejamento: precisamos criar um jogo da memoria, e cada uma das cartas sao jogos, exemplo cobrinha, dama, velha e outros classicos... se uma pessoa achar o par, o adversario e ele joga aquele jogo, se ele for de par, mas se for jogo indivisual, o adversario deve jogar....",
    "at": "2026-06-30T23:53:47.544Z"
  },
  {
    "id": "1782863178166qzerx61swu",
    "agentId": "coord_qa",
    "agentName": "Diana Test",
    "agentAvatar": "🔍",
    "action": "closed",
    "ticketKey": "KAN-1935",
    "ticketSummary": "[QA] Validação: crie um jogo da cobeinha classico, que joga sozinho e roda sozinho,\n",
    "at": "2026-06-30T23:46:18.166Z"
  },
  {
    "id": "1782863175824686cjkkpeuo",
    "agentId": "coord_qa",
    "agentName": "Diana Test",
    "agentAvatar": "🔍",
    "action": "progressing",
    "ticketKey": "KAN-1935",
    "ticketSummary": "[QA] Validação: crie um jogo da cobeinha classico, que joga sozinho e roda sozinho,\n",
    "at": "2026-06-30T23:46:15.824Z"
  },
  {
    "id": "1782863174596h4nw36uyap",
    "agentId": "coord_qa",
    "agentName": "Diana Test",
    "agentAvatar": "🔍",
    "action": "opened",
    "ticketKey": "...",
    "ticketSummary": "[QA] Validação: crie um jogo da cobeinha classico, que joga sozinho e roda sozinho,\n",
    "at": "2026-06-30T23:46:14.596Z"
  },
  {
    "id": "17828631745954bb7hhv1eyt",
    "agentId": "sr_dev",
    "agentName": "David Dev",
    "agentAvatar": "⚡",
    "action": "closed",
    "ticketKey": "KAN-1934",
    "ticketSummary": "[DEV] Implementação: crie um jogo da cobeinha classico, que joga sozinho e roda sozinho,\n",
    "at": "2026-06-30T23:46:14.595Z"
  },
  {
    "id": "17828631724444eca5nan4ze",
    "agentId": "sr_dev",
    "agentName": "David Dev",
    "agentAvatar": "⚡",
    "action": "progressing",
    "ticketKey": "KAN-1934",
    "ticketSummary": "[DEV] Implementação: crie um jogo da cobeinha classico, que joga sozinho e roda sozinho,\n",
    "at": "2026-06-30T23:46:12.444Z"
  },
  {
    "id": "1782863171408bfcz9pmw8mn",
    "agentId": "sr_dev",
    "agentName": "David Dev",
    "agentAvatar": "⚡",
    "action": "opened",
    "ticketKey": "...",
    "ticketSummary": "[DEV] Implementação: crie um jogo da cobeinha classico, que joga sozinho e roda sozinho,\n",
    "at": "2026-06-30T23:46:11.408Z"
  },
  {
    "id": "1782863171406s76db1qixx",
    "agentId": "sr_ux",
    "agentName": "Elsa Pixel",
    "agentAvatar": "✨",
    "action": "closed",
    "ticketKey": "KAN-1933",
    "ticketSummary": "[UX] Design: crie um jogo da cobeinha classico, que joga sozinho e roda sozinho,\n",
    "at": "2026-06-30T23:46:11.406Z"
  },
  {
    "id": "17828631689189ri2q66ry8t",
    "agentId": "sr_ux",
    "agentName": "Elsa Pixel",
    "agentAvatar": "✨",
    "action": "progressing",
    "ticketKey": "KAN-1933",
    "ticketSummary": "[UX] Design: crie um jogo da cobeinha classico, que joga sozinho e roda sozinho,\n",
    "at": "2026-06-30T23:46:08.918Z"
  },
  {
    "id": "1782863167269gkjqc9uzj3i",
    "agentId": "sr_ux",
    "agentName": "Elsa Pixel",
    "agentAvatar": "✨",
    "action": "opened",
    "ticketKey": "...",
    "ticketSummary": "[UX] Design: crie um jogo da cobeinha classico, que joga sozinho e roda sozinho,\n",
    "at": "2026-06-30T23:46:07.269Z"
  },
  {
    "id": "1782863167267kgkuctg4zoh",
    "agentId": "mgr_prod",
    "agentName": "Sarah Backlog",
    "agentAvatar": "📋",
    "action": "closed",
    "ticketKey": "KAN-1932",
    "ticketSummary": "[PM] Planejamento: crie um jogo da cobeinha classico, que joga sozinho e roda sozinho,\n",
    "at": "2026-06-30T23:46:07.267Z"
  },
  {
    "id": "1782863165167ctdzwir2sxs",
    "agentId": "mgr_prod",
    "agentName": "Sarah Backlog",
    "agentAvatar": "📋",
    "action": "progressing",
    "ticketKey": "KAN-1932",
    "ticketSummary": "[PM] Planejamento: crie um jogo da cobeinha classico, que joga sozinho e roda sozinho,\n",
    "at": "2026-06-30T23:46:05.167Z"
  },
  {
    "id": "1782863162615nstrgyt888h",
    "agentId": "mgr_prod",
    "agentName": "Sarah Backlog",
    "agentAvatar": "📋",
    "action": "opened",
    "ticketKey": "...",
    "ticketSummary": "[PM] Planejamento: crie um jogo da cobeinha classico, que joga sozinho e roda sozinho,\n",
    "at": "2026-06-30T23:46:02.615Z"
  },
  {
    "id": "17828628597424wbsr12k4cv",
    "agentId": "coord_qa",
    "agentName": "Diana Test",
    "agentAvatar": "🔍",
    "action": "closed",
    "ticketKey": "KAN-1931",
    "ticketSummary": "[QA] Validação: eu qro um sistema de gameficacao que todo mundo ame, e queria fazer o melhor possível",
    "at": "2026-06-30T23:40:59.742Z"
  },
  {
    "id": "17828628572664pxphtg3ux7",
    "agentId": "coord_qa",
    "agentName": "Diana Test",
    "agentAvatar": "🔍",
    "action": "progressing",
    "ticketKey": "KAN-1931",
    "ticketSummary": "[QA] Validação: eu qro um sistema de gameficacao que todo mundo ame, e queria fazer o melhor possível",
    "at": "2026-06-30T23:40:57.266Z"
  },
  {
    "id": "17828628562351jac8e9ha5zi",
    "agentId": "coord_qa",
    "agentName": "Diana Test",
    "agentAvatar": "🔍",
    "action": "opened",
    "ticketKey": "...",
    "ticketSummary": "[QA] Validação: eu qro um sistema de gameficacao que todo mundo ame, e queria fazer o melhor possível",
    "at": "2026-06-30T23:40:56.235Z"
  },
  {
    "id": "1782862856234bsy7x0ev5wf",
    "agentId": "sr_dev",
    "agentName": "David Dev",
    "agentAvatar": "⚡",
    "action": "closed",
    "ticketKey": "KAN-1930",
    "ticketSummary": "[DEV] Implementação: eu qro um sistema de gameficacao que todo mundo ame, e queria fazer o melhor possível",
    "at": "2026-06-30T23:40:56.234Z"
  },
  {
    "id": "1782862854111b10kne3y776",
    "agentId": "sr_dev",
    "agentName": "David Dev",
    "agentAvatar": "⚡",
    "action": "progressing",
    "ticketKey": "KAN-1930",
    "ticketSummary": "[DEV] Implementação: eu qro um sistema de gameficacao que todo mundo ame, e queria fazer o melhor possível",
    "at": "2026-06-30T23:40:54.111Z"
  },
  {
    "id": "1782862852680uvtgo7b07z",
    "agentId": "sr_dev",
    "agentName": "David Dev",
    "agentAvatar": "⚡",
    "action": "opened",
    "ticketKey": "...",
    "ticketSummary": "[DEV] Implementação: eu qro um sistema de gameficacao que todo mundo ame, e queria fazer o melhor possível",
    "at": "2026-06-30T23:40:52.680Z"
  },
  {
    "id": "178286285267828qc3qzrwyp",
    "agentId": "sr_ux",
    "agentName": "Elsa Pixel",
    "agentAvatar": "✨",
    "action": "closed",
    "ticketKey": "KAN-1929",
    "ticketSummary": "[UX] Design: eu qro um sistema de gameficacao que todo mundo ame, e queria fazer o melhor possível",
    "at": "2026-06-30T23:40:52.678Z"
  },
  {
    "id": "1782862850222oldg4tb8hg",
    "agentId": "sr_ux",
    "agentName": "Elsa Pixel",
    "agentAvatar": "✨",
    "action": "progressing",
    "ticketKey": "KAN-1929",
    "ticketSummary": "[UX] Design: eu qro um sistema de gameficacao que todo mundo ame, e queria fazer o melhor possível",
    "at": "2026-06-30T23:40:50.222Z"
  },
  {
    "id": "1782862848778uq9af1d5by8",
    "agentId": "sr_ux",
    "agentName": "Elsa Pixel",
    "agentAvatar": "✨",
    "action": "opened",
    "ticketKey": "...",
    "ticketSummary": "[UX] Design: eu qro um sistema de gameficacao que todo mundo ame, e queria fazer o melhor possível",
    "at": "2026-06-30T23:40:48.778Z"
  },
  {
    "id": "1782862848776qqp8mmxljaf",
    "agentId": "mgr_prod",
    "agentName": "Sarah Backlog",
    "agentAvatar": "📋",
    "action": "closed",
    "ticketKey": "KAN-1928",
    "ticketSummary": "[PM] Planejamento: eu qro um sistema de gameficacao que todo mundo ame, e queria fazer o melhor possível",
    "at": "2026-06-30T23:40:48.776Z"
  },
  {
    "id": "1782862846203qim503fllnn",
    "agentId": "mgr_prod",
    "agentName": "Sarah Backlog",
    "agentAvatar": "📋",
    "action": "progressing",
    "ticketKey": "KAN-1928",
    "ticketSummary": "[PM] Planejamento: eu qro um sistema de gameficacao que todo mundo ame, e queria fazer o melhor possível",
    "at": "2026-06-30T23:40:46.203Z"
  },
  {
    "id": "17828628444053l3dlu5sdfh",
    "agentId": "mgr_prod",
    "agentName": "Sarah Backlog",
    "agentAvatar": "📋",
    "action": "opened",
    "ticketKey": "...",
    "ticketSummary": "[PM] Planejamento: eu qro um sistema de gameficacao que todo mundo ame, e queria fazer o melhor possível",
    "at": "2026-06-30T23:40:44.405Z"
  },
  {
    "id": "1782862035938pv5a1hhrjy",
    "agentId": "coord_qa",
    "agentName": "Diana Test",
    "agentAvatar": "🔍",
    "action": "closed",
    "ticketKey": "KAN-1925",
    "ticketSummary": "[QA] Validação: crie um jogo estilo GTA 6",
    "at": "2026-06-30T23:27:15.938Z"
  },
  {
    "id": "17828620341435d2qisudzua",
    "agentId": "coord_qa",
    "agentName": "Diana Test",
    "agentAvatar": "🔍",
    "action": "progressing",
    "ticketKey": "KAN-1925",
    "ticketSummary": "[QA] Validação: crie um jogo estilo GTA 6",
    "at": "2026-06-30T23:27:14.143Z"
  },
  {
    "id": "1782862032699celjskmd9jo",
    "agentId": "coord_qa",
    "agentName": "Diana Test",
    "agentAvatar": "🔍",
    "action": "opened",
    "ticketKey": "...",
    "ticketSummary": "[QA] Validação: crie um jogo estilo GTA 6",
    "at": "2026-06-30T23:27:12.699Z"
  },
  {
    "id": "17828620326980e4bk60a21u",
    "agentId": "sr_dev",
    "agentName": "David Dev",
    "agentAvatar": "⚡",
    "action": "closed",
    "ticketKey": "KAN-1924",
    "ticketSummary": "[DEV] Implementação: crie um jogo estilo GTA 6",
    "at": "2026-06-30T23:27:12.698Z"
  },
  {
    "id": "1782862030539nzm6nfl881e",
    "agentId": "sr_dev",
    "agentName": "David Dev",
    "agentAvatar": "⚡",
    "action": "progressing",
    "ticketKey": "KAN-1924",
    "ticketSummary": "[DEV] Implementação: crie um jogo estilo GTA 6",
    "at": "2026-06-30T23:27:10.539Z"
  },
  {
    "id": "178286202916371lhjcxy4mw",
    "agentId": "sr_dev",
    "agentName": "David Dev",
    "agentAvatar": "⚡",
    "action": "opened",
    "ticketKey": "...",
    "ticketSummary": "[DEV] Implementação: crie um jogo estilo GTA 6",
    "at": "2026-06-30T23:27:09.163Z"
  },
  {
    "id": "1782862029161zfuqytx5tcr",
    "agentId": "sr_ux",
    "agentName": "Elsa Pixel",
    "agentAvatar": "✨",
    "action": "closed",
    "ticketKey": "KAN-1923",
    "ticketSummary": "[UX] Design: crie um jogo estilo GTA 6",
    "at": "2026-06-30T23:27:09.161Z"
  },
  {
    "id": "1782862026684y8aig7hlym",
    "agentId": "sr_ux",
    "agentName": "Elsa Pixel",
    "agentAvatar": "✨",
    "action": "progressing",
    "ticketKey": "KAN-1923",
    "ticketSummary": "[UX] Design: crie um jogo estilo GTA 6",
    "at": "2026-06-30T23:27:06.684Z"
  },
  {
    "id": "178286202531642nwe0epf66",
    "agentId": "sr_ux",
    "agentName": "Elsa Pixel",
    "agentAvatar": "✨",
    "action": "opened",
    "ticketKey": "...",
    "ticketSummary": "[UX] Design: crie um jogo estilo GTA 6",
    "at": "2026-06-30T23:27:05.316Z"
  },
  {
    "id": "17828620253146wselmdhk53",
    "agentId": "mgr_prod",
    "agentName": "Sarah Backlog",
    "agentAvatar": "📋",
    "action": "closed",
    "ticketKey": "KAN-1922",
    "ticketSummary": "[PM] Planejamento: crie um jogo estilo GTA 6",
    "at": "2026-06-30T23:27:05.314Z"
  },
  {
    "id": "17828620228795aev4xptnr2",
    "agentId": "mgr_prod",
    "agentName": "Sarah Backlog",
    "agentAvatar": "📋",
    "action": "progressing",
    "ticketKey": "KAN-1922",
    "ticketSummary": "[PM] Planejamento: crie um jogo estilo GTA 6",
    "at": "2026-06-30T23:27:02.879Z"
  },
  {
    "id": "1782862021303nbobojwm6hk",
    "agentId": "mgr_prod",
    "agentName": "Sarah Backlog",
    "agentAvatar": "📋",
    "action": "opened",
    "ticketKey": "...",
    "ticketSummary": "[PM] Planejamento: crie um jogo estilo GTA 6",
    "at": "2026-06-30T23:27:01.303Z"
  },
  {
    "id": "1782861531444iyqgbmgyy8",
    "agentId": "coord_qa",
    "agentName": "Diana Test",
    "agentAvatar": "🔍",
    "action": "closed",
    "ticketKey": "KAN-1920",
    "ticketSummary": "[QA] Validação: cria um jogo da velha 4",
    "at": "2026-06-30T23:18:51.444Z"
  },
  {
    "id": "1782861529565nej4vf6ew",
    "agentId": "coord_qa",
    "agentName": "Diana Test",
    "agentAvatar": "🔍",
    "action": "progressing",
    "ticketKey": "KAN-1920",
    "ticketSummary": "[QA] Validação: cria um jogo da velha 4",
    "at": "2026-06-30T23:18:49.565Z"
  },
  {
    "id": "1782861528123vlo8q0ow6m",
    "agentId": "coord_qa",
    "agentName": "Diana Test",
    "agentAvatar": "🔍",
    "action": "opened",
    "ticketKey": "...",
    "ticketSummary": "[QA] Validação: cria um jogo da velha 4",
    "at": "2026-06-30T23:18:48.123Z"
  },
  {
    "id": "1782861528121v0s3i5k20k",
    "agentId": "sr_dev",
    "agentName": "David Dev",
    "agentAvatar": "⚡",
    "action": "closed",
    "ticketKey": "KAN-1919",
    "ticketSummary": "[DEV] Implementação: cria um jogo da velha 4",
    "at": "2026-06-30T23:18:48.121Z"
  },
  {
    "id": "1782861526017yvn05c4xai",
    "agentId": "sr_dev",
    "agentName": "David Dev",
    "agentAvatar": "⚡",
    "action": "progressing",
    "ticketKey": "KAN-1919",
    "ticketSummary": "[DEV] Implementação: cria um jogo da velha 4",
    "at": "2026-06-30T23:18:46.017Z"
  },
  {
    "id": "1782861524604hfj68s4qw4n",
    "agentId": "sr_dev",
    "agentName": "David Dev",
    "agentAvatar": "⚡",
    "action": "opened",
    "ticketKey": "...",
    "ticketSummary": "[DEV] Implementação: cria um jogo da velha 4",
    "at": "2026-06-30T23:18:44.604Z"
  },
  {
    "id": "178286152460286xnu4eno8w",
    "agentId": "sr_ux",
    "agentName": "Elsa Pixel",
    "agentAvatar": "✨",
    "action": "closed",
    "ticketKey": "KAN-1918",
    "ticketSummary": "[UX] Design: cria um jogo da velha 4",
    "at": "2026-06-30T23:18:44.602Z"
  },
  {
    "id": "1782861522079k5e7chj611",
    "agentId": "sr_ux",
    "agentName": "Elsa Pixel",
    "agentAvatar": "✨",
    "action": "progressing",
    "ticketKey": "KAN-1918",
    "ticketSummary": "[UX] Design: cria um jogo da velha 4",
    "at": "2026-06-30T23:18:42.079Z"
  },
  {
    "id": "17828615205046li7a0haj0r",
    "agentId": "sr_ux",
    "agentName": "Elsa Pixel",
    "agentAvatar": "✨",
    "action": "opened",
    "ticketKey": "...",
    "ticketSummary": "[UX] Design: cria um jogo da velha 4",
    "at": "2026-06-30T23:18:40.504Z"
  },
  {
    "id": "1782861520504pde9syh0t9g",
    "agentId": "mgr_prod",
    "agentName": "Sarah Backlog",
    "agentAvatar": "📋",
    "action": "closed",
    "ticketKey": "KAN-1917",
    "ticketSummary": "[PM] Planejamento: cria um jogo da velha 4",
    "at": "2026-06-30T23:18:40.504Z"
  },
  {
    "id": "1782861518289369cjyzkwrb",
    "agentId": "mgr_prod",
    "agentName": "Sarah Backlog",
    "agentAvatar": "📋",
    "action": "progressing",
    "ticketKey": "KAN-1917",
    "ticketSummary": "[PM] Planejamento: cria um jogo da velha 4",
    "at": "2026-06-30T23:18:38.289Z"
  },
  {
    "id": "1782861517121yspeoovgehf",
    "agentId": "mgr_prod",
    "agentName": "Sarah Backlog",
    "agentAvatar": "📋",
    "action": "opened",
    "ticketKey": "...",
    "ticketSummary": "[PM] Planejamento: cria um jogo da velha 4",
    "at": "2026-06-30T23:18:37.122Z"
  },
  {
    "id": "1782859723267n5pgwm33up9",
    "agentId": "coord_qa",
    "agentName": "Diana Test",
    "agentAvatar": "🔍",
    "action": "closed",
    "ticketKey": "KAN-1915",
    "ticketSummary": "[QA] Validação: cria um jogo da velha 3",
    "at": "2026-06-30T22:48:43.267Z"
  },
  {
    "id": "1782859720789cy93fhou6vg",
    "agentId": "coord_qa",
    "agentName": "Diana Test",
    "agentAvatar": "🔍",
    "action": "progressing",
    "ticketKey": "KAN-1915",
    "ticketSummary": "[QA] Validação: cria um jogo da velha 3",
    "at": "2026-06-30T22:48:40.789Z"
  },
  {
    "id": "1782859719815q6amzcxez6",
    "agentId": "coord_qa",
    "agentName": "Diana Test",
    "agentAvatar": "🔍",
    "action": "opened",
    "ticketKey": "...",
    "ticketSummary": "[QA] Validação: cria um jogo da velha 3",
    "at": "2026-06-30T22:48:39.815Z"
  },
  {
    "id": "1782859719814lznfqsfgbjd",
    "agentId": "sr_dev",
    "agentName": "David Dev",
    "agentAvatar": "⚡",
    "action": "closed",
    "ticketKey": "KAN-1914",
    "ticketSummary": "[DEV] Implementação: cria um jogo da velha 3",
    "at": "2026-06-30T22:48:39.814Z"
  },
  {
    "id": "178285971758556x8jkdg0if",
    "agentId": "sr_dev",
    "agentName": "David Dev",
    "agentAvatar": "⚡",
    "action": "progressing",
    "ticketKey": "KAN-1914",
    "ticketSummary": "[DEV] Implementação: cria um jogo da velha 3",
    "at": "2026-06-30T22:48:37.585Z"
  },
  {
    "id": "1782859716000f2f28wsx0eg",
    "agentId": "sr_dev",
    "agentName": "David Dev",
    "agentAvatar": "⚡",
    "action": "opened",
    "ticketKey": "...",
    "ticketSummary": "[DEV] Implementação: cria um jogo da velha 3",
    "at": "2026-06-30T22:48:36.000Z"
  },
  {
    "id": "1782859715998r163uefjlvi",
    "agentId": "sr_ux",
    "agentName": "Elsa Pixel",
    "agentAvatar": "✨",
    "action": "closed",
    "ticketKey": "KAN-1913",
    "ticketSummary": "[UX] Design: cria um jogo da velha 3",
    "at": "2026-06-30T22:48:35.998Z"
  },
  {
    "id": "1782859713704b0fo00rkhc",
    "agentId": "sr_ux",
    "agentName": "Elsa Pixel",
    "agentAvatar": "✨",
    "action": "progressing",
    "ticketKey": "KAN-1913",
    "ticketSummary": "[UX] Design: cria um jogo da velha 3",
    "at": "2026-06-30T22:48:33.704Z"
  },
  {
    "id": "17828597122124wvkwbxzf34",
    "agentId": "sr_ux",
    "agentName": "Elsa Pixel",
    "agentAvatar": "✨",
    "action": "opened",
    "ticketKey": "...",
    "ticketSummary": "[UX] Design: cria um jogo da velha 3",
    "at": "2026-06-30T22:48:32.212Z"
  },
  {
    "id": "1782859712210ygy07b85dzh",
    "agentId": "mgr_prod",
    "agentName": "Sarah Backlog",
    "agentAvatar": "📋",
    "action": "closed",
    "ticketKey": "KAN-1912",
    "ticketSummary": "[PM] Planejamento: cria um jogo da velha 3",
    "at": "2026-06-30T22:48:32.210Z"
  },
  {
    "id": "178285970994433a1ln6307t",
    "agentId": "mgr_prod",
    "agentName": "Sarah Backlog",
    "agentAvatar": "📋",
    "action": "progressing",
    "ticketKey": "KAN-1912",
    "ticketSummary": "[PM] Planejamento: cria um jogo da velha 3",
    "at": "2026-06-30T22:48:29.944Z"
  },
  {
    "id": "1782859708300isodpl7ppxk",
    "agentId": "mgr_prod",
    "agentName": "Sarah Backlog",
    "agentAvatar": "📋",
    "action": "opened",
    "ticketKey": "...",
    "ticketSummary": "[PM] Planejamento: cria um jogo da velha 3",
    "at": "2026-06-30T22:48:28.300Z"
  },
  {
    "id": "1782858276587wekugqpmjw",
    "agentId": "coord_qa",
    "agentName": "Diana Test",
    "agentAvatar": "🔍",
    "action": "closed",
    "ticketKey": "KAN-1910",
    "ticketSummary": "[QA] Validação: cria um jogo da velha 2",
    "at": "2026-06-30T22:24:36.587Z"
  },
  {
    "id": "17828582746465r0oqofucwr",
    "agentId": "coord_qa",
    "agentName": "Diana Test",
    "agentAvatar": "🔍",
    "action": "progressing",
    "ticketKey": "KAN-1910",
    "ticketSummary": "[QA] Validação: cria um jogo da velha 2",
    "at": "2026-06-30T22:24:34.646Z"
  },
  {
    "id": "1782858273669z5iszm5svvr",
    "agentId": "coord_qa",
    "agentName": "Diana Test",
    "agentAvatar": "🔍",
    "action": "opened",
    "ticketKey": "...",
    "ticketSummary": "[QA] Validação: cria um jogo da velha 2",
    "at": "2026-06-30T22:24:33.669Z"
  },
  {
    "id": "1782858273667hhcpnnoe0rp",
    "agentId": "sr_dev",
    "agentName": "David Dev",
    "agentAvatar": "⚡",
    "action": "closed",
    "ticketKey": "KAN-1909",
    "ticketSummary": "[DEV] Implementação: cria um jogo da velha 2",
    "at": "2026-06-30T22:24:33.667Z"
  },
  {
    "id": "17828582717157v6zttk0dim",
    "agentId": "sr_dev",
    "agentName": "David Dev",
    "agentAvatar": "⚡",
    "action": "progressing",
    "ticketKey": "KAN-1909",
    "ticketSummary": "[DEV] Implementação: cria um jogo da velha 2",
    "at": "2026-06-30T22:24:31.715Z"
  },
  {
    "id": "1782858270571unwsr275spg",
    "agentId": "sr_dev",
    "agentName": "David Dev",
    "agentAvatar": "⚡",
    "action": "opened",
    "ticketKey": "...",
    "ticketSummary": "[DEV] Implementação: cria um jogo da velha 2",
    "at": "2026-06-30T22:24:30.571Z"
  },
  {
    "id": "1782858270568jxmvtldf7z",
    "agentId": "sr_ux",
    "agentName": "Elsa Pixel",
    "agentAvatar": "✨",
    "action": "closed",
    "ticketKey": "KAN-1908",
    "ticketSummary": "[UX] Design: cria um jogo da velha 2",
    "at": "2026-06-30T22:24:30.568Z"
  },
  {
    "id": "1782858268360zlijzje8yfo",
    "agentId": "sr_ux",
    "agentName": "Elsa Pixel",
    "agentAvatar": "✨",
    "action": "progressing",
    "ticketKey": "KAN-1908",
    "ticketSummary": "[UX] Design: cria um jogo da velha 2",
    "at": "2026-06-30T22:24:28.360Z"
  },
  {
    "id": "1782858267314cx821fwk85i",
    "agentId": "sr_ux",
    "agentName": "Elsa Pixel",
    "agentAvatar": "✨",
    "action": "opened",
    "ticketKey": "...",
    "ticketSummary": "[UX] Design: cria um jogo da velha 2",
    "at": "2026-06-30T22:24:27.314Z"
  },
  {
    "id": "1782858267313ezzploa0enb",
    "agentId": "mgr_prod",
    "agentName": "Sarah Backlog",
    "agentAvatar": "📋",
    "action": "closed",
    "ticketKey": "KAN-1907",
    "ticketSummary": "[PM] Planejamento: cria um jogo da velha 2",
    "at": "2026-06-30T22:24:27.313Z"
  },
  {
    "id": "1782858264958887tl9ow8kh",
    "agentId": "mgr_prod",
    "agentName": "Sarah Backlog",
    "agentAvatar": "📋",
    "action": "progressing",
    "ticketKey": "KAN-1907",
    "ticketSummary": "[PM] Planejamento: cria um jogo da velha 2",
    "at": "2026-06-30T22:24:24.958Z"
  },
  {
    "id": "17828582633297pkga8a2xzv",
    "agentId": "mgr_prod",
    "agentName": "Sarah Backlog",
    "agentAvatar": "📋",
    "action": "opened",
    "ticketKey": "...",
    "ticketSummary": "[PM] Planejamento: cria um jogo da velha 2",
    "at": "2026-06-30T22:24:23.329Z"
  },
  {
    "id": "1782858048278f2ble3ll8xv",
    "agentId": "coord_qa",
    "agentName": "Diana Test",
    "agentAvatar": "🔍",
    "action": "closed",
    "ticketKey": "KAN-1905",
    "ticketSummary": "[QA] Validação: cria um jogo da velha",
    "at": "2026-06-30T22:20:48.278Z"
  },
  {
    "id": "17828580460385mvm000tja7",
    "agentId": "coord_qa",
    "agentName": "Diana Test",
    "agentAvatar": "🔍",
    "action": "progressing",
    "ticketKey": "KAN-1905",
    "ticketSummary": "[QA] Validação: cria um jogo da velha",
    "at": "2026-06-30T22:20:46.038Z"
  },
  {
    "id": "17828580445112f9enn5ux16",
    "agentId": "coord_qa",
    "agentName": "Diana Test",
    "agentAvatar": "🔍",
    "action": "opened",
    "ticketKey": "...",
    "ticketSummary": "[QA] Validação: cria um jogo da velha",
    "at": "2026-06-30T22:20:44.511Z"
  },
  {
    "id": "17828580445100strkjh9tq4e",
    "agentId": "sr_dev",
    "agentName": "David Dev",
    "agentAvatar": "⚡",
    "action": "closed",
    "ticketKey": "KAN-1904",
    "ticketSummary": "[DEV] Implementação: cria um jogo da velha",
    "at": "2026-06-30T22:20:44.510Z"
  },
  {
    "id": "1782858042748keuenkrl9fb",
    "agentId": "sr_dev",
    "agentName": "David Dev",
    "agentAvatar": "⚡",
    "action": "progressing",
    "ticketKey": "KAN-1904",
    "ticketSummary": "[DEV] Implementação: cria um jogo da velha",
    "at": "2026-06-30T22:20:42.748Z"
  },
  {
    "id": "1782858041427qryjs6rb4p",
    "agentId": "sr_dev",
    "agentName": "David Dev",
    "agentAvatar": "⚡",
    "action": "opened",
    "ticketKey": "...",
    "ticketSummary": "[DEV] Implementação: cria um jogo da velha",
    "at": "2026-06-30T22:20:41.427Z"
  },
  {
    "id": "1782858041425mqfs5sobaqa",
    "agentId": "sr_ux",
    "agentName": "Elsa Pixel",
    "agentAvatar": "✨",
    "action": "closed",
    "ticketKey": "KAN-1903",
    "ticketSummary": "[UX] Design: cria um jogo da velha",
    "at": "2026-06-30T22:20:41.425Z"
  },
  {
    "id": "1782858039130p3ftt55bonf",
    "agentId": "sr_ux",
    "agentName": "Elsa Pixel",
    "agentAvatar": "✨",
    "action": "progressing",
    "ticketKey": "KAN-1903",
    "ticketSummary": "[UX] Design: cria um jogo da velha",
    "at": "2026-06-30T22:20:39.130Z"
  },
  {
    "id": "178285803763671q512e96g6",
    "agentId": "sr_ux",
    "agentName": "Elsa Pixel",
    "agentAvatar": "✨",
    "action": "opened",
    "ticketKey": "...",
    "ticketSummary": "[UX] Design: cria um jogo da velha",
    "at": "2026-06-30T22:20:37.636Z"
  },
  {
    "id": "1782858037635mn7etw9bfwa",
    "agentId": "mgr_prod",
    "agentName": "Sarah Backlog",
    "agentAvatar": "📋",
    "action": "closed",
    "ticketKey": "KAN-1902",
    "ticketSummary": "[PM] Planejamento: cria um jogo da velha",
    "at": "2026-06-30T22:20:37.635Z"
  },
  {
    "id": "1782858035350bkw6l4svqsh",
    "agentId": "mgr_prod",
    "agentName": "Sarah Backlog",
    "agentAvatar": "📋",
    "action": "progressing",
    "ticketKey": "KAN-1902",
    "ticketSummary": "[PM] Planejamento: cria um jogo da velha",
    "at": "2026-06-30T22:20:35.350Z"
  },
  {
    "id": "1782858033902wwao0navpx",
    "agentId": "mgr_prod",
    "agentName": "Sarah Backlog",
    "agentAvatar": "📋",
    "action": "opened",
    "ticketKey": "...",
    "ticketSummary": "[PM] Planejamento: cria um jogo da velha",
    "at": "2026-06-30T22:20:33.902Z"
  }
]